flet_table/__init__.py
flet_table/editable_table.py
flet_table/elements.py
flet_table/hash_pass_functools.py
flet_table/table.py
flet_table/v1/__init__.py
flet_table/v1/build_filter_query.py
flet_table/v1/elements.py
flet_table-2.1.3.dist-info/METADATA
flet_table-2.1.3.dist-info/WHEEL
flet_table-2.1.3.dist-info/top_level.txt
flet_table-2.1.3.dist-info/RECORD
