Metadata-Version: 2.4
Name: flet_table
Version: 2.1.3
Summary: This library provides normal table elements by just using flet framework
Home-page: https://github.com/tzinchy/flet_table
Author: Luchiano Farrely
Author-email: dreevxqcrypto@gmail.com
Classifier: Programming Language :: Python :: 3
Classifier: License :: OSI Approved :: MIT License
Classifier: Operating System :: OS Independent
Requires-Python: >=3.6
Requires-Dist: anyio==4.9.0
Requires-Dist: bcrypt==4.3.0
Requires-Dist: certifi==2025.1.31
Requires-Dist: et_xmlfile==2.0.0
Requires-Dist: flet==0.27.6
Requires-Dist: flet-desktop==0.27.6
Requires-Dist: h11==0.14.0
Requires-Dist: httpcore==1.0.8
Requires-Dist: httpx==0.28.1
Requires-Dist: idna==3.10
Requires-Dist: iniconfig==2.1.0
Requires-Dist: numpy==2.2.4
Requires-Dist: oauthlib==3.2.2
Requires-Dist: openpyxl==3.1.5
Requires-Dist: packaging==24.2
Requires-Dist: pandas==2.2.3
Requires-Dist: pluggy==1.5.0
Requires-Dist: PyMySQL==1.1.1
Requires-Dist: pytest==8.3.5
Requires-Dist: python-dateutil==2.9.0.post0
Requires-Dist: pytz==2025.2
Requires-Dist: repath==0.9.0
Requires-Dist: simpledatatable==0.3.4
Requires-Dist: six==1.17.0
Requires-Dist: sniffio==1.3.1
Requires-Dist: SQLAlchemy==2.0.40
Requires-Dist: typing_extensions==4.13.2
Requires-Dist: tzdata==2025.2
Dynamic: author
Dynamic: author-email
Dynamic: classifier
Dynamic: description
Dynamic: description-content-type
Dynamic: home-page
Dynamic: requires-dist
Dynamic: requires-python
Dynamic: summary
